ConvertGeoJson/__init__.py
ConvertGeoJson/__main__.py
ConvertGeoJson/convertGeoJson.py
ConvertGeoJson-1.0.6.dist-info/LICENSE
ConvertGeoJson-1.0.6.dist-info/METADATA
ConvertGeoJson-1.0.6.dist-info/WHEEL
ConvertGeoJson-1.0.6.dist-info/entry_points.txt
ConvertGeoJson-1.0.6.dist-info/top_level.txt
ConvertGeoJson-1.0.6.dist-info/RECORD
