Metadata-Version: 2.1
Name: ConvertGeoJson
Version: 1.0.6
Summary: Converts a GeoJSON file from L-EST97 Estonian Coordinate System of 1997 to WGS84
Home-page: https://github.com/GlebRed/est97-to-wgs84-convertor
Author: Gleb Redko
Author-email: gleb.redko@gmail.com
License: UNKNOWN
Platform: UNKNOWN
Classifier: Development Status :: 5 - Production/Stable
Classifier: Intended Audience :: Developers
Classifier: License :: OSI Approved :: MIT License
Classifier: Programming Language :: Python :: 3
Classifier: Programming Language :: Python :: 3.6
Classifier: Programming Language :: Python :: 3.7
Classifier: Programming Language :: Python :: 3.8
Classifier: Programming Language :: Python :: 3.9
Requires-Dist: pyproj
Requires-Dist: tqdm
